{
  "timestamp": "2025-11-14T12:00:00.0000000Z",
  "version": "1.0.0.0",
  "environment": {
    "os": "Microsoft Windows NT 10.0.22631.0",
    "framework": ".NET 8.0.0",
    "process": "C:/Users/jaakk/Desktop/Gradu/ShipHydroSim/ShipHydroSim.App/bin/Release/net8.0/ShipHydroSim.App.exe"
  },
  "seed": 424242,
  "parameters": {
    "MaxParticles": 3000,
    "TargetFps": 30,
    "AdaptiveTimeStep": true,
    "SmoothingLength": 0.2,
    "RestDensity": 1000.0,
    "Stiffness": 20000.0,
    "Viscosity": 0.05,
    "WavesEnabled": true,
    "WaveType": "Sine"
  }
}
